{
  "positive": {
    "list": [
      "hoop*",
      "hope*",
      "gehoopt",
      "uitzien",
      "uitgezien",
      "vooruitzien*",
      "vooruitzicht*",
      "vooruitblik",
      "blikte",
      "vertrouw*",
      "geestdrift*",
      "belofte",
      "beloof*",
      "inspiratie",
      "inspireer*",
      "ontplooi*",
      "passie",
      "gepassioneerd",
      "ge\u00efnspireerd",
      "opgelucht",
      "toekomstvisie",
      "toekomstgericht*",
      "toekomstbestendig*",
      "houvast",
      "toevlucht",
      "toeverlaat",
      "perspectief",
      "redd*",
      "gered",
      "herstel*"
    ],
    "except_when": [
      "hopeloos",
      "hopeloze"
    ]
  },
  "negative": {
    "list": [
      "vrees*",
      "vreze*",
      "gevreesd*",
      "schrik*",
      "schrok*",
      "geschrokken",
      "paniek",
      "angst*",
      "doodsangst*",
      "bang*",
      "doodsbang*",
      "nood",
      "noodlot*",
      "radeloos*",
      "beducht*",
      "bezorgd*",
      "benard*",
      "benauwd*",
      "beklem*",
      "ingeklem*",
      "verwar*",
      "overbelast*",
      "beroering",
      "beroerd*",
      "commotie",
      "ongerust*",
      " onrust*",
      "verontrust*",
      "stress*",
      "nerveus*",
      "nervositeit",
      "spanning*",
      "gespannen*",
      "kommer",
      "kwel"
    ],
    "except_when": [
      "bangladesh",
      "bangalore",
      "bangkok"
    ]
  }
}